[
  {"id":"https://kodeverk.no/arkiv/noark/systemid/FJELL","displayName":"Fjellnettverkett"},
  {"id":"https://kodeverk.no/arkiv/noark/systemid/INNSYN","displayName":"Innsynsbegjæringer"},
  {"id":"https://kodeverk.no/arkiv/noark/systemid/OPPL","displayName":"Kompetanse"},
  {"id":"https://kodeverk.no/arkiv/noark/systemid/OESMU","displayName":"Møte"},
  {"id":"https://kodeverk.no/arkiv/noark/systemid/MU","displayName":"Møte- og utvalg"},
  {"id":"https://kodeverk.no/arkiv/noark/systemid/PERS","displayName":"Personalmapper"},
  {"id":"https://kodeverk.no/arkiv/noark/systemid/PRES","displayName":"Presedenssaker"},
  {"id":"https://kodeverk.no/arkiv/noark/systemid/SAK","displayName":"Sakarkiv"},
  {"id":"https://kodeverk.no/arkiv/noark/systemid/ANSV","displayName":"Saksansvarlig"},
  {"id":"https://kodeverk.no/arkiv/noark/systemid/SAKSMAPPED","displayName":"Saksmappedokument"},
  {"id":"https://kodeverk.no/arkiv/noark/systemid/OESSAK","displayName":"Samarbeid Sak"},
  {"id":"https://kodeverk.no/arkiv/noark/systemid/SKYSS","displayName":"Skoleskyss"},
  {"id":"https://kodeverk.no/arkiv/noark/systemid/OKO","displayName":"Økonomi"}
]