{
    "content": [
        {
            "id": 1,
            "displayName": "test t2t",
            "fromApplicationId": 2,
            "fromTypeId": "text",
            "toApplicationId": "fylkesrad",
            "toTypeId": "text",
            "convertingMap": {
                "ac1": "https://kodeverk/format/systemid/AC1",
                "excel": "https://kodeverk/format/systemid/XLSX",
                "word": "https://kodeverk/format/systemid/DOCX"
            }
        },
        {
            "id": 2,
            "displayName": "test m2f",
            "fromApplicationId": 2,
            "fromTypeId": "mediatype",
            "toApplicationId": "fylkesrad",
            "toTypeId": "filformat",
            "convertingMap": {
                "ac3": "https://kodeverk/format/systemid/AC3",
                "excel": "https://kodeverk/format/systemid/XLSX",
                "word": "https://kodeverk/format/systemid/DOCX"
            }
        },
        {
            "id": 3,
            "displayName": "test t2t2",
            "fromApplicationId": 2,
            "fromTypeId": "text",
            "toApplicationId": "fylkesrad",
            "toTypeId": "text"
        },
        {
            "id": 4,
            "displayName": "test m2f3",
            "fromApplicationId": 2,
            "fromTypeId": "mediatype",
            "toApplicationId": "fylkesrad",
            "toTypeId": "filformat"
        },
        {
            "id": 5,
            "displayName": "test5",
            "fromApplicationId": 2,
            "fromTypeId": "text",
            "toApplicationId": "fylkesrad",
            "toTypeId": "text"
        },
        {
            "id": 6,
            "displayName": "test6",
            "fromApplicationId": 2,
            "fromTypeId": "mediatype",
            "toApplicationId": "fylkesrad",
            "toTypeId": "filformat"
        },
        {
            "id": 7,
            "displayName": "test7 t2t2",
            "fromApplicationId": 2,
            "fromTypeId": "text",
            "toApplicationId": "fylkesrad",
            "toTypeId": "text"
        },
        {
            "id": 8,
            "displayName": "test8 m2f3",
            "fromApplicationId": 2,
            "fromTypeId": "mediatype",
            "toApplicationId": "fylkesrad",
            "toTypeId": "filformat"
        },
        {
            "id": 9,
            "displayName": "test9 next page",
            "fromApplicationId": 2,
            "fromTypeId": "text",
            "toApplicationId": "fylkesrad",
            "toTypeId": "text"
        },
        {
            "id": 10,
            "displayName": "test10 m2f3",
            "fromApplicationId": 2,
            "fromTypeId": "mediatype",
            "toApplicationId": "fylkesrad",
            "toTypeId": "filformat"
        }
    ],
    "pageable": {
        "sort": {
            "empty": false,
            "sorted": true,
            "unsorted": false
        },
        "offset": 0,
        "pageNumber": 0,
        "pageSize": 100,
        "paged": true,
        "unpaged": false
    },
    "last": true,
    "totalPages": 1,
    "totalElements": 6,
    "first": true,
    "size": 100,
    "number": 0,
    "sort": {
        "empty": false,
        "sorted": true,
        "unsorted": false
    },
    "numberOfElements": 6,
    "empty": false
}
